prismo/__init__.py
prismo/cli.py
prismo/analysis/__init__.py
prismo/analysis/sparameters.py
prismo/backends/__init__.py
prismo/backends/backend_manager.py
prismo/backends/base.py
prismo/backends/cuda_kernels.py
prismo/backends/cupy_backend.py
prismo/backends/numpy_backend.py
prismo/boundaries/__init__.py
prismo/boundaries/mode_port.py
prismo/boundaries/pml.py
prismo/core/__init__.py
prismo/core/fields.py
prismo/core/grid.py
prismo/core/simulation.py
prismo/core/solver.py
prismo/geometry/__init__.py
prismo/geometry/shapes.py
prismo/io/__init__.py
prismo/io/exporters/__init__.py
prismo/io/exporters/base.py
prismo/io/exporters/csv_exporter.py
prismo/io/exporters/parquet_exporter.py
prismo/io/lumerical/__init__.py
prismo/io/lumerical/fsp_parser.py
prismo/io/lumerical/material_db.py
prismo/materials/__init__.py
prismo/materials/ade.py
prismo/materials/dispersion.py
prismo/materials/library.py
prismo/materials/tensor.py
prismo/modes/__init__.py
prismo/modes/solver.py
prismo/monitors/__init__.py
prismo/monitors/base.py
prismo/monitors/dft.py
prismo/monitors/field.py
prismo/monitors/flux.py
prismo/monitors/mode_monitor.py
prismo/optimization/__init__.py
prismo/optimization/sweep.py
prismo/solvers/__init__.py
prismo/sources/__init__.py
prismo/sources/base.py
prismo/sources/gaussian.py
prismo/sources/mode.py
prismo/sources/plane_wave.py
prismo/sources/point.py
prismo/sources/tfsf.py
prismo/sources/waveform.py
prismo/utils/__init__.py
prismo/utils/mode_matching.py
prismo/visualization/__init__.py
pyprismo-0.0.1.dist-info/METADATA
pyprismo-0.0.1.dist-info/WHEEL
pyprismo-0.0.1.dist-info/entry_points.txt
pyprismo-0.0.1.dist-info/licenses/LICENSE
pyprismo-0.0.1.dist-info/RECORD
