Metadata-Version: 2.4
Name: pyprismo
Version: 0.0.1
Summary: A high-performance Python-based FDTD solver for waveguide photonics
Project-URL: Homepage, https://github.com/rithulkamesh/prismo
Project-URL: Documentation, https://prismo.readthedocs.io
Project-URL: Repository, https://github.com/rithulkamesh/prismo.git
Project-URL: Issues, https://github.com/rithulkamesh/prismo/issues
Author-email: Rithul Kamesh <hello@rithul.dev>
License: MIT License
License-File: LICENSE
Keywords: electromagnetic,fdtd,photonics,simulation,waveguide
Classifier: Development Status :: 3 - Alpha
Classifier: Intended Audience :: Science/Research
Classifier: License :: OSI Approved :: MIT License
Classifier: Operating System :: OS Independent
Classifier: Programming Language :: Python :: 3
Classifier: Programming Language :: Python :: 3.9
Classifier: Programming Language :: Python :: 3.10
Classifier: Programming Language :: Python :: 3.11
Classifier: Programming Language :: Python :: 3.12
Classifier: Topic :: Scientific/Engineering :: Mathematics
Classifier: Topic :: Scientific/Engineering :: Physics
Requires-Python: >=3.9
Requires-Dist: h5py>=3.0.0
Requires-Dist: matplotlib>=3.4.0
Requires-Dist: numpy>=1.21.0
Requires-Dist: polars>=0.20.0
Requires-Dist: psutil>=5.9.0
Requires-Dist: pydantic>=2.0.0
Requires-Dist: rich>=10.0.0
Requires-Dist: scipy>=1.7.0
Requires-Dist: tqdm>=4.60.0
Provides-Extra: acceleration
Requires-Dist: cupy-cuda12x>=12.0.0; (platform_machine == 'x86_64') and extra == 'acceleration'
Requires-Dist: numba>=0.58.0; extra == 'acceleration'
Provides-Extra: all
Requires-Dist: prismo[acceleration,dev,docs,visualization]; extra == 'all'
Provides-Extra: dev
Requires-Dist: black>=22.0.0; extra == 'dev'
Requires-Dist: flake8>=4.0.0; extra == 'dev'
Requires-Dist: isort>=5.10.0; extra == 'dev'
Requires-Dist: mypy>=0.950; extra == 'dev'
Requires-Dist: pre-commit>=2.15.0; extra == 'dev'
Requires-Dist: pytest-benchmark>=3.4.0; extra == 'dev'
Requires-Dist: pytest-cov>=3.0.0; extra == 'dev'
Requires-Dist: pytest-xdist>=2.5.0; extra == 'dev'
Requires-Dist: pytest>=6.2.0; extra == 'dev'
Requires-Dist: ruff>=0.1.0; extra == 'dev'
Provides-Extra: docs
Requires-Dist: ipykernel>=6.0.0; extra == 'docs'
Requires-Dist: jupyter>=1.0.0; extra == 'docs'
Requires-Dist: myst-parser>=0.17.0; extra == 'docs'
Requires-Dist: nbsphinx>=0.8.0; extra == 'docs'
Requires-Dist: sphinx-autodoc-typehints>=1.12.0; extra == 'docs'
Requires-Dist: sphinx-rtd-theme>=1.0.0; extra == 'docs'
Requires-Dist: sphinx>=4.0.0; extra == 'docs'
Provides-Extra: visualization
Requires-Dist: mayavi>=4.7.0; extra == 'visualization'
Requires-Dist: plotly>=5.0.0; extra == 'visualization'
Requires-Dist: pyvista>=0.32.0; extra == 'visualization'
Requires-Dist: vtk>=9.0.0; extra == 'visualization'
